gather_vision_gov_au_plugin/__init__.py
gather_vision_gov_au_plugin/plugin.py
gather_vision_gov_au_plugin/air/__init__.py
gather_vision_gov_au_plugin/air/qld.py
gather_vision_gov_au_plugin/election/__init__.py
gather_vision_gov_au_plugin/election/national.py
gather_vision_gov_au_plugin/election/qld.py
gather_vision_gov_au_plugin/electricity/__init__.py
gather_vision_gov_au_plugin/electricity/qld_energex.py
gather_vision_gov_au_plugin/electricity/qld_ergon_energy.py
gather_vision_gov_au_plugin/government/__init__.py
gather_vision_gov_au_plugin/government/national.py
gather_vision_gov_au_plugin/government/qld.py
gather_vision_gov_au_plugin/petition/__init__.py
gather_vision_gov_au_plugin/petition/national.py
gather_vision_gov_au_plugin/petition/qld.py
gather_vision_gov_au_plugin/petition/qld_bne.py
gather_vision_gov_au_plugin/resources/__init__.py
gather_vision_gov_au_plugin/transport/__init__.py
gather_vision_gov_au_plugin/transport/qld_bne_translink.py
gather_vision_gov_au_plugin/transport/qld_fuel.py
gather_vision_gov_au_plugin/transport/qld_rail.py
gather_vision_gov_au_plugin/water/__init__.py
gather_vision_gov_au_plugin/water/national_bom_river_height.py
gather_vision_gov_au_plugin/water/qld_bne.py
gather_vision_gov_au_plugin/water/qld_tmba.py
gather_vision_gov_au_plugin-0.0.1.dist-info/LICENSE
gather_vision_gov_au_plugin-0.0.1.dist-info/METADATA
gather_vision_gov_au_plugin-0.0.1.dist-info/WHEEL
gather_vision_gov_au_plugin-0.0.1.dist-info/entry_points.txt
gather_vision_gov_au_plugin-0.0.1.dist-info/top_level.txt
gather_vision_gov_au_plugin-0.0.1.dist-info/RECORD
