Metadata-Version: 2.1
Name: gather-vision-gov-au-plugin
Version: 0.0.1
Summary: A gather-vision plugin for obtaining data from Australian governments.
Project-URL: Homepage, https://github.com/anotherbyte-net/gather-vision-gov-au-plugin
Project-URL: Changelog, https://github.com/anotherbyte-net/gather-vision-gov-au-plugin/blob/main/CHANGELOG.md
Project-URL: Source, https://github.com/anotherbyte-net/gather-vision-gov-au-plugin
Project-URL: Tracker, https://github.com/anotherbyte-net/gather-vision-gov-au-plugin/issues
Classifier: Development Status :: 2 - Pre-Alpha
Classifier: License :: OSI Approved :: Apache Software License
Classifier: Operating System :: POSIX :: Linux
Classifier: Operating System :: Microsoft :: Windows
Classifier: Environment :: Console
Classifier: Programming Language :: Python
Classifier: Programming Language :: Python :: 3
Classifier: Programming Language :: Python :: 3 :: Only
Classifier: Programming Language :: Python :: 3.7
Classifier: Programming Language :: Python :: 3.8
Classifier: Programming Language :: Python :: 3.9
Classifier: Programming Language :: Python :: 3.10
Classifier: Programming Language :: Python :: 3.11
Classifier: Topic :: Software Development :: Libraries :: Python Modules
Classifier: Topic :: Scientific/Engineering :: Information Analysis
Classifier: Topic :: Utilities
Requires-Python: >=3.7
License-File: LICENSE
Requires-Dist: importlib-resources (~=5.9)
Requires-Dist: typing-extensions (~=4.3)
Requires-Dist: gather-vision (~=0.0.3)
Requires-Dist: leaf-focus (~=0.5)
Requires-Dist: importlib-metadata (~=4.2) ; python_version < "3.8"
Requires-Dist: typing-inspect (~=0.8) ; python_version < "3.8"
Requires-Dist: importlib-metadata (~=5.0) ; python_version >= "3.8"
Provides-Extra: dev
Requires-Dist: pip (~=22.2) ; extra == 'dev'
Requires-Dist: setuptools (~=65.3) ; extra == 'dev'
Requires-Dist: wheel (~=0.37) ; extra == 'dev'
Requires-Dist: build (~=0.8) ; extra == 'dev'
Requires-Dist: twine (~=4.0) ; extra == 'dev'
Requires-Dist: pytest (~=7.1) ; extra == 'dev'
Requires-Dist: pytest-mock (~=3.9) ; extra == 'dev'
Requires-Dist: pytest-cov (~=4.0) ; extra == 'dev'
Requires-Dist: tblib (~=1.7) ; extra == 'dev'
Requires-Dist: tox (~=3.26) ; extra == 'dev'
Requires-Dist: coverage (~=6.5) ; extra == 'dev'
Requires-Dist: hypothesis (~=6.55) ; extra == 'dev'
Requires-Dist: black (~=22.8) ; extra == 'dev'
Requires-Dist: flake8 (~=5.0) ; extra == 'dev'
Requires-Dist: flake8-annotations-coverage (~=0.0) ; extra == 'dev'
Requires-Dist: flake8-black (~=0.3) ; extra == 'dev'
Requires-Dist: flake8-bugbear (~=22.9) ; extra == 'dev'
Requires-Dist: flake8-comprehensions (~=3.10) ; extra == 'dev'
Requires-Dist: flake8-unused-arguments (~=0.0) ; extra == 'dev'
Requires-Dist: flake8-requirements (~=1.7) ; extra == 'dev'
Requires-Dist: mypy (~=0.981) ; extra == 'dev'
Requires-Dist: pylint (~=2.15) ; extra == 'dev'
Requires-Dist: pydocstyle[toml] (~=6.1) ; extra == 'dev'
Requires-Dist: pyright (~=1.1) ; extra == 'dev'
Requires-Dist: types-dateparser (~=1.1) ; extra == 'dev'
Requires-Dist: types-PyYAML (~=6.0) ; extra == 'dev'
Requires-Dist: types-requests (~=2.28) ; extra == 'dev'
Requires-Dist: types-backports (~=0.1) ; extra == 'dev'
Requires-Dist: types-urllib3 (~=1.26) ; extra == 'dev'
Requires-Dist: pdoc (~=12.0) ; extra == 'dev'
Requires-Dist: pyre-check (~=0.9) ; (platform_system != "Windows") and extra == 'dev'
Requires-Dist: pytype (~=2022.8) ; (python_version <= "3.10" and platform_system != "Windows") and extra == 'dev'
